ehdnexact/__init__.py
ehdnexact/main.py
EHdnExact-0.1.1.dist-info/LICENSE
EHdnExact-0.1.1.dist-info/METADATA
EHdnExact-0.1.1.dist-info/WHEEL
EHdnExact-0.1.1.dist-info/entry_points.txt
EHdnExact-0.1.1.dist-info/top_level.txt
EHdnExact-0.1.1.dist-info/RECORD
