Metadata-Version: 2.1
Name: EHdnExact
Version: 0.1.1
Summary: Refines approximate repeat regions identified by ExpansionHunter denovo to exact genomic coordinates
Home-page: https://github.com/rashidalabri/ehdnexact
Author: Rashid Al-Abri
Author-email: hello@rashidalabri.com
License-File: LICENSE
Requires-Dist: biopython
Requires-Dist: pysam
Requires-Dist: tqdm
